remarkable_update_fuse.cpython-312-x86_64-linux-gnu.so
remarkable_update_fuse.pyi
remarkable_update_fuse-1.3.1.dist-info/METADATA
remarkable_update_fuse-1.3.1.dist-info/WHEEL
remarkable_update_fuse-1.3.1.dist-info/entry_points.txt
remarkable_update_fuse-1.3.1.dist-info/top_level.txt
remarkable_update_fuse-1.3.1.dist-info/RECORD
remarkable_update_fuse-1.3.1.dist-info/licenses/LICENSE
