Metadata-Version: 2.4
Name: remarkable_update_fuse
Version: 1.3.1
Summary: Userspace filesystem for remarkable update files
Author-email: Eeems <eeems@eeems.email>
Project-URL: Homepage, https://github.com/Eeems-Org/remarkable-update-fuse
Project-URL: Repository, https://github.com/Eeems-Org/remarkable-update-fuse.git
Project-URL: Issues, https://github.com/Eeems-Org/remarkable-update-fuse/issues
Classifier: Development Status :: 5 - Production/Stable
Classifier: Environment :: Console
Classifier: Intended Audience :: Developers
Classifier: License :: OSI Approved :: MIT License
Classifier: Operating System :: POSIX :: Linux
Classifier: Programming Language :: Python :: 3 :: Only
Classifier: Programming Language :: Python :: 3
Classifier: Programming Language :: Python :: 3.11
Classifier: Programming Language :: Python :: 3.12
Classifier: Programming Language :: Python :: 3.13
Classifier: Topic :: System :: Filesystems
Classifier: Topic :: Utilities
Requires-Python: <3.14,>=3.11
License-File: LICENSE
Requires-Dist: fuse-python==1.0.9
Requires-Dist: remarkable-update-image==1.3.1
Dynamic: license-file
